README.md
setup.py
nocturnal_davaydeploy/__init__.py
nocturnal_davaydeploy/flag.py
nocturnal_davaydeploy.egg-info/PKG-INFO
nocturnal_davaydeploy.egg-info/SOURCES.txt
nocturnal_davaydeploy.egg-info/dependency_links.txt
nocturnal_davaydeploy.egg-info/top_level.txt