Metadata-Version: 1.0
Name: nocturnal-davaydeploy
Version: 0.0.1
Summary: My perfect lib that returns something
Home-page: UNKNOWN
Author: nocturnalq
Author-email: UNKNOWN
License: UNKNOWN
Platform: UNKNOWN
